wtforms_bootstrap5/__init__.py
wtforms_bootstrap5/context.py
wtforms_bootstrap5/helpers.py
wtforms_bootstrap5/registry.py
wtforms_bootstrap5/renderers.py
wtforms_bootstrap5-0.3.0.dist-info/LICENSE
wtforms_bootstrap5-0.3.0.dist-info/WHEEL
wtforms_bootstrap5-0.3.0.dist-info/METADATA
wtforms_bootstrap5-0.3.0.dist-info/RECORD
