Metadata-Version: 2.1
Name: wtforms-bootstrap5
Version: 0.3.0
Summary: Simple library for rendering WTForms in HTML as Bootstrap 5 form controls
Home-page: https://github.com/LaunchPlatform/wtforms-bootstrap5
License: MIT
Author: Fang-Pen Lin
Author-email: fangpen@launchplatform.com
Requires-Python: >=3.8,<4.0
Classifier: License :: OSI Approved :: MIT License
Classifier: Programming Language :: Python :: 3
Classifier: Programming Language :: Python :: 3.10
Classifier: Programming Language :: Python :: 3.8
Classifier: Programming Language :: Python :: 3.9
Requires-Dist: WTForms (>=3.0.1,<4.0.0)
Project-URL: Repository, https://github.com/LaunchPlatform/wtforms-bootstrap5
